.DS_Store
hatchbuck.py
hatchbuck-1.0.4.dist-info/DESCRIPTION.rst
hatchbuck-1.0.4.dist-info/METADATA
hatchbuck-1.0.4.dist-info/RECORD
hatchbuck-1.0.4.dist-info/WHEEL
hatchbuck-1.0.4.dist-info/metadata.json
hatchbuck-1.0.4.dist-info/top_level.txt
