Metadata-Version: 2.0
Name: hatchbuck
Version: 1.0.4
Summary: Hatchbuck.com CRM API bindings for python
Home-page: https://github.com/vshn/python-hatchbuck
Author: VSHN AG, Bashar Said
Author-email: bashar.said@vshn.ch
License: BSD
Keywords: hatchbuck CRM API
Platform: UNKNOWN
Requires-Dist: requests (>=2)
Requires-Dist: pycountry (>=1)
